{
	"37" :{
		"number" : "37",
		"name" : " الصّٰۤفّٰت",
		"name_latin" : "A\u1e63-\u1e62\u0101ff\u0101t",
		"surah_translation" : "Barisan-Barisan",
		"number_of_ayah" : "182",
		"location" : "Makkiyah",
		"text" : {
			"1" : "وَالصّٰۤفّٰتِ صَفًّاۙ",
			"2" : "فَالزّٰجِرٰتِ زَجْرًاۙ",
			"3" : "فَالتّٰلِيٰتِ ذِكْرًاۙ",
			"4" : "اِنَّ اِلٰهَكُمْ لَوَاحِدٌۗ ",
			"5" : "رَبُّ السَّمٰوٰتِ وَالْاَرْضِ وَمَا بَيْنَهُمَا وَرَبُّ الْمَشَارِقِۗ ",
			"6" : "اِنَّا زَيَّنَّا السَّمَاۤءَ الدُّنْيَا بِزِيْنَةِ ِۨالْكَوَاكِبِۙ",
			"7" : "وَحِفْظًا مِّنْ كُلِّ شَيْطٰنٍ مَّارِدٍۚ ",
			"8" : "لَا يَسَّمَّعُوْنَ اِلَى الْمَلَاِ الْاَعْلٰى وَيُقْذَفُوْنَ مِنْ كُلِّ جَانِبٍۖ ",
			"9" : "دُحُوْرًا وَّلَهُمْ عَذَابٌ وَّاصِبٌ ",
			"10" : "اِلَّا مَنْ خَطِفَ الْخَطْفَةَ فَاَتْبَعَهٗ شِهَابٌ ثَاقِبٌ ",
			"11" : "فَاسْتَفْتِهِمْ اَهُمْ اَشَدُّ خَلْقًا اَمْ مَّنْ خَلَقْنَا ۗاِنَّا خَلَقْنٰهُمْ مِّنْ طِيْنٍ لَّازِبٍ ",
			"12" : "بَلْ عَجِبْتَ وَيَسْخَرُوْنَ ۖ ",
			"13" : "وَاِذَا ذُكِّرُوْا لَا يَذْكُرُوْنَ ۖ ",
			"14" : "وَاِذَا رَاَوْا اٰيَةً يَّسْتَسْخِرُوْنَۖ ",
			"15" : "وَقَالُوْٓا اِنْ هٰذَآ اِلَّا سِحْرٌ مُّبِيْنٌ ۚ ",
			"16" : "ءَاِذَا مِتْنَا وَكُنَّا تُرَابًا وَّعِظَامًا ءَاِنَّا لَمَبْعُوْثُوْنَۙ",
			"17" : "اَوَاٰبَاۤؤُنَا الْاَوَّلُوْنَۗ ",
			"18" : "قُلْ نَعَمْ وَاَنْتُمْ دٰخِرُوْنَۚ ",
			"19" : "فَاِنَّمَا هِيَ زَجْرَةٌ وَّاحِدَةٌ فَاِذَا هُمْ يَنْظُرُوْنَ ",
			"20" : "وَقَالُوْا يٰوَيْلَنَا هٰذَا يَوْمُ الدِّيْنِ ",
			"21" : "هٰذَا يَوْمُ الْفَصْلِ الَّذِيْ كُنْتُمْ بِهٖ تُكَذِّبُوْنَ ࣖ",
			"22" : "اُحْشُرُوا الَّذِيْنَ ظَلَمُوْا وَاَزْوَاجَهُمْ وَمَا كَانُوْا يَعْبُدُوْنَ ۙ",
			"23" : "مِنْ دُوْنِ اللّٰهِ فَاهْدُوْهُمْ اِلٰى صِرَاطِ الْجَحِيْمِ ",
			"24" : "وَقِفُوْهُمْ اِنَّهُمْ مَّسْـُٔوْلُوْنَ ۙ",
			"25" : "مَا لَكُمْ لَا تَنَاصَرُوْنَ ",
			"26" : "بَلْ هُمُ الْيَوْمَ مُسْتَسْلِمُوْنَ",
			"27" : "وَاَقْبَلَ بَعْضُهُمْ عَلٰى بَعْضٍ يَّتَسَاۤءَلُوْنَ ",
			"28" : "قَالُوْٓا اِنَّكُمْ كُنْتُمْ تَأْتُوْنَنَا عَنِ الْيَمِيْنِ ",
			"29" : "قَالُوْا بَلْ لَّمْ تَكُوْنُوْا مُؤْمِنِيْنَۚ ",
			"30" : "وَمَا كَانَ لَنَا عَلَيْكُمْ مِّنْ سُلْطٰنٍۚ بَلْ كُنْتُمْ قَوْمًا طٰغِيْنَ ",
			"31" : "فَحَقَّ عَلَيْنَا قَوْلُ رَبِّنَآ  ۖاِنَّا لَذَاۤىِٕقُوْنَ ",
			"32" : "فَاَغْوَيْنٰكُمْ اِنَّا كُنَّا غٰوِيْنَ ",
			"33" : "فَاِنَّهُمْ يَوْمَىِٕذٍ فِى الْعَذَابِ مُشْتَرِكُوْنَ",
			"34" : "اِنَّا كَذٰلِكَ نَفْعَلُ بِالْمُجْرِمِيْنَ",
			"35" : "اِنَّهُمْ كَانُوْٓا اِذَا قِيْلَ لَهُمْ لَآ اِلٰهَ اِلَّا اللّٰهُ يَسْتَكْبِرُوْنَ ۙ",
			"36" : "وَيَقُوْلُوْنَ اَىِٕنَّا لَتَارِكُوْٓا اٰلِهَتِنَا لِشَاعِرٍ مَّجْنُوْنٍ ۗ ",
			"37" : "بَلْ جَاۤءَ بِالْحَقِّ وَصَدَّقَ الْمُرْسَلِيْنَ",
			"38" : "اِنَّكُمْ لَذَاۤىِٕقُوا الْعَذَابِ الْاَلِيْمِ ۚ ",
			"39" : "وَمَا تُجْزَوْنَ اِلَّا مَا كُنْتُمْ تَعْمَلُوْنَۙ",
			"40" : "اِلَّا عِبَادَ اللّٰهِ الْمُخْلَصِيْنَ ",
			"41" : "اُولٰۤىِٕكَ لَهُمْ رِزْقٌ مَّعْلُوْمٌۙ",
			"42" : "فَوَاكِهُ ۚوَهُمْ مُّكْرَمُوْنَۙ",
			"43" : "فِيْ جَنّٰتِ النَّعِيْمِۙ",
			"44" : "عَلٰى سُرُرٍ مُّتَقٰبِلِيْنَ",
			"45" : "يُطَافُ عَلَيْهِمْ بِكَأْسٍ مِّنْ مَّعِيْنٍۢ ۙ",
			"46" : "بَيْضَاۤءَ لَذَّةٍ لِّلشّٰرِبِيْنَۚ ",
			"47" : "لَا فِيْهَا غَوْلٌ وَّلَا هُمْ عَنْهَا يُنْزَفُوْنَ",
			"48" : "وَعِنْدَهُمْ قٰصِرٰتُ الطَّرْفِ عِيْنٌ ۙ",
			"49" : "كَاَنَّهُنَّ بَيْضٌ مَّكْنُوْنٌ",
			"50" : "فَاَقْبَلَ بَعْضُهُمْ عَلٰى بَعْضٍ يَّتَسَاۤءَلُوْنَ",
			"51" : "قَالَ قَاۤىِٕلٌ مِّنْهُمْ اِنِّيْ كَانَ لِيْ قَرِيْنٌۙ",
			"52" : "يَّقُوْلُ اَءِنَّكَ لَمِنَ الْمُصَدِّقِيْنَ",
			"53" : "ءَاِذَا مِتْنَا وَكُنَّا تُرَابًا وَّعِظَامًا ءَاِنَّا لَمَدِيْنُوْنَ",
			"54" : "قَالَ هَلْ اَنْتُمْ مُّطَّلِعُوْنَ",
			"55" : "فَاطَّلَعَ فَرَاٰهُ فِيْ سَوَاۤءِ الْجَحِيْمِ",
			"56" : "قَالَ تَاللّٰهِ اِنْ كِدْتَّ لَتُرْدِيْنِ ۙ",
			"57" : "وَلَوْلَا نِعْمَةُ رَبِّيْ لَكُنْتُ مِنَ الْمُحْضَرِيْنَ",
			"58" : "اَفَمَا نَحْنُ بِمَيِّتِيْنَۙ",
			"59" : "اِلَّا مَوْتَتَنَا الْاُوْلٰى وَمَا نَحْنُ بِمُعَذَّبِيْنَ",
			"60" : "اِنَّ هٰذَا لَهُوَ الْفَوْزُ الْعَظِيْمُ",
			"61" : "لِمِثْلِ هٰذَا فَلْيَعْمَلِ الْعٰمِلُوْنَ",
			"62" : "اَذٰلِكَ خَيْرٌ نُّزُلًا اَمْ شَجَرَةُ الزَّقُّوْمِ",
			"63" : "اِنَّا جَعَلْنٰهَا فِتْنَةً لِّلظّٰلِمِيْنَ",
			"64" : "اِنَّهَا شَجَرَةٌ تَخْرُجُ فِيْٓ اَصْلِ الْجَحِيْمِۙ",
			"65" : "طَلْعُهَا كَاَنَّهٗ رُءُوْسُ الشَّيٰطِيْنِ",
			"66" : "فَاِنَّهُمْ لَاٰكِلُوْنَ مِنْهَا فَمَالِـُٔوْنَ مِنْهَا الْبُطُوْنَۗ ",
			"67" : "ثُمَّ اِنَّ لَهُمْ عَلَيْهَا لَشَوْبًا مِّنْ حَمِيْمٍۚ ",
			"68" : "ثُمَّ اِنَّ مَرْجِعَهُمْ لَاِلَى الْجَحِيْمِ",
			"69" : "اِنَّهُمْ اَلْفَوْا اٰبَاۤءَهُمْ ضَاۤلِّيْنَۙ",
			"70" : "فَهُمْ عَلٰٓى اٰثٰرِهِمْ يُهْرَعُوْنَ",
			"71" : "وَلَقَدْ ضَلَّ قَبْلَهُمْ اَكْثَرُ الْاَوَّلِيْنَۙ",
			"72" : "وَلَقَدْ اَرْسَلْنَا فِيْهِمْ مُّنْذِرِيْنَ",
			"73" : "فَانْظُرْ كَيْفَ كَانَ عَاقِبَةُ الْمُنْذَرِيْنَۙ",
			"74" : "اِلَّا عِبَادَ اللّٰهِ الْمُخْلَصِيْنَ ࣖ ",
			"75" : "وَلَقَدْ نَادٰىنَا نُوْحٌ فَلَنِعْمَ الْمُجِيْبُوْنَۖ ",
			"76" : "وَنَجَّيْنٰهُ وَاَهْلَهٗ مِنَ الْكَرْبِ الْعَظِيْمِۖ ",
			"77" : "وَجَعَلْنَا ذُرِّيَّتَهٗ هُمُ الْبَاقِيْنَ",
			"78" : "وَتَرَكْنَا عَلَيْهِ فِى الْاٰخِرِيْنَ ۖ ",
			"79" : "سَلٰمٌ عَلٰى نُوْحٍ فِى الْعٰلَمِيْنَ",
			"80" : "اِنَّا كَذٰلِكَ نَجْزِى الْمُحْسِنِيْنَ",
			"81" : "اِنَّهٗ مِنْ عِبَادِنَا الْمُؤْمِنِيْنَ",
			"82" : "ثُمَّ اَغْرَقْنَا الْاٰخَرِيْنَ",
			"83" : "۞ وَاِنَّ مِنْ شِيْعَتِهٖ لَاِبْرٰهِيْمَ ۘ ",
			"84" : "اِذْ جَاۤءَ رَبَّهٗ بِقَلْبٍ سَلِيْمٍۙ",
			"85" : "اِذْ قَالَ لِاَبِيْهِ وَقَوْمِهٖ مَاذَا تَعْبُدُوْنَ ۚ ",
			"86" : "اَىِٕفْكًا اٰلِهَةً دُوْنَ اللّٰهِ تُرِيْدُوْنَۗ ",
			"87" : "فَمَا ظَنُّكُمْ بِرَبِّ الْعٰلَمِيْنَ",
			"88" : "فَنَظَرَ نَظْرَةً فِى النُّجُوْمِۙ",
			"89" : "فَقَالَ اِنِّيْ سَقِيْمٌ",
			"90" : "فَتَوَلَّوْا عَنْهُ مُدْبِرِيْنَ",
			"91" : "فَرَاغَ اِلٰٓى اٰلِهَتِهِمْ فَقَالَ اَلَا تَأْكُلُوْنَۚ ",
			"92" : "مَا لَكُمْ لَا تَنْطِقُوْنَ",
			"93" : "فَرَاغَ عَلَيْهِمْ ضَرْبًا ۢبِالْيَمِيْنِ",
			"94" : "فَاَقْبَلُوْٓا اِلَيْهِ يَزِفُّوْنَ",
			"95" : "قَالَ اَتَعْبُدُوْنَ مَا تَنْحِتُوْنَۙ",
			"96" : "وَاللّٰهُ خَلَقَكُمْ وَمَا تَعْمَلُوْنَ",
			"97" : "قَالُوا ابْنُوْا لَهٗ بُنْيَانًا فَاَلْقُوْهُ فِى الْجَحِيْمِ",
			"98" : "فَاَرَادُوْا بِهٖ كَيْدًا فَجَعَلْنٰهُمُ الْاَسْفَلِيْنَ",
			"99" : "وَقَالَ اِنِّيْ ذَاهِبٌ اِلٰى رَبِّيْ سَيَهْدِيْنِ",
			"100" : "رَبِّ هَبْ لِيْ مِنَ الصّٰلِحِيْنَ",
			"101" : "فَبَشَّرْنٰهُ بِغُلٰمٍ حَلِيْمٍ",
			"102" : "فَلَمَّا بَلَغَ مَعَهُ السَّعْيَ قَالَ يٰبُنَيَّ اِنِّيْٓ اَرٰى فِى الْمَنَامِ اَنِّيْٓ اَذْبَحُكَ فَانْظُرْ مَاذَا تَرٰىۗ قَالَ يٰٓاَبَتِ افْعَلْ مَا تُؤْمَرُۖ سَتَجِدُنِيْٓ اِنْ شَاۤءَ اللّٰهُ مِنَ الصّٰبِرِيْنَ",
			"103" : "فَلَمَّآ اَسْلَمَا وَتَلَّهٗ لِلْجَبِيْنِۚ ",
			"104" : "وَنَادَيْنٰهُ اَنْ يّٰٓاِبْرٰهِيْمُ ۙ",
			"105" : "قَدْ صَدَّقْتَ الرُّءْيَا ۚاِنَّا كَذٰلِكَ نَجْزِى الْمُحْسِنِيْنَ",
			"106" : "اِنَّ هٰذَا لَهُوَ الْبَلٰۤؤُا الْمُبِيْنُ",
			"107" : "وَفَدَيْنٰهُ بِذِبْحٍ عَظِيْمٍ",
			"108" : "وَتَرَكْنَا عَلَيْهِ فِى الْاٰخِرِيْنَ ۖ ",
			"109" : "سَلٰمٌ عَلٰٓى اِبْرٰهِيْمَ",
			"110" : "كَذٰلِكَ نَجْزِى الْمُحْسِنِيْنَ",
			"111" : "اِنَّهٗ مِنْ عِبَادِنَا الْمُؤْمِنِيْنَ",
			"112" : "وَبَشَّرْنٰهُ بِاِسْحٰقَ نَبِيًّا مِّنَ الصّٰلِحِيْنَ",
			"113" : "وَبٰرَكْنَا عَلَيْهِ وَعَلٰٓى اِسْحٰقَۗ وَمِنْ ذُرِّيَّتِهِمَا مُحْسِنٌ وَّظَالِمٌ لِّنَفْسِهٖ مُبِيْنٌ ࣖ",
			"114" : "وَلَقَدْ مَنَنَّا عَلٰى مُوْسٰى وَهٰرُوْنَ ۚ ",
			"115" : "وَنَجَّيْنٰهُمَا وَقَوْمَهُمَا مِنَ الْكَرْبِ الْعَظِيْمِۚ ",
			"116" : "وَنَصَرْنٰهُمْ فَكَانُوْا هُمُ الْغٰلِبِيْنَۚ ",
			"117" : "وَاٰتَيْنٰهُمَا الْكِتٰبَ الْمُسْتَبِيْنَ ۚ ",
			"118" : "وَهَدَيْنٰهُمَا الصِّرَاطَ الْمُسْتَقِيْمَۚ ",
			"119" : "وَتَرَكْنَا عَلَيْهِمَا فِى الْاٰخِرِيْنَ ۖ ",
			"120" : "سَلٰمٌ عَلٰى مُوْسٰى وَهٰرُوْنَ",
			"121" : "اِنَّا كَذٰلِكَ نَجْزِى الْمُحْسِنِيْنَ",
			"122" : "اِنَّهُمَا مِنْ عِبَادِنَا الْمُؤْمِنِيْنَ",
			"123" : "وَاِنَّ اِلْيَاسَ لَمِنَ الْمُرْسَلِيْنَۗ ",
			"124" : "اِذْ قَالَ لِقَوْمِهٖٓ اَلَا تَتَّقُوْنَ",
			"125" : "اَتَدْعُوْنَ بَعْلًا وَّتَذَرُوْنَ اَحْسَنَ الْخٰلِقِيْنَۙ",
			"126" : "اللّٰهَ رَبَّكُمْ وَرَبَّ اٰبَاۤىِٕكُمُ الْاَوَّلِيْنَ",
			"127" : "فَكَذَّبُوْهُ فَاِنَّهُمْ لَمُحْضَرُوْنَۙ",
			"128" : "اِلَّا عِبَادَ اللّٰهِ الْمُخْلَصِيْنَ",
			"129" : "وَتَرَكْنَا عَلَيْهِ فِى الْاٰخِرِيْنَ ۙ",
			"130" : "سَلٰمٌ عَلٰٓى اِلْ يَاسِيْنَ",
			"131" : "اِنَّا كَذٰلِكَ نَجْزِى الْمُحْسِنِيْنَ",
			"132" : "اِنَّهٗ مِنْ عِبَادِنَا الْمُؤْمِنِيْنَ",
			"133" : "وَاِنَّ لُوْطًا لَّمِنَ الْمُرْسَلِيْنَۗ ",
			"134" : "اِذْ نَجَّيْنٰهُ وَاَهْلَهٗٓ اَجْمَعِيْنَۙ",
			"135" : "اِلَّا عَجُوْزًا فِى الْغٰبِرِيْنَ",
			"136" : "ثُمَّ دَمَّرْنَا الْاٰخَرِيْنَ",
			"137" : "وَاِنَّكُمْ لَتَمُرُّوْنَ عَلَيْهِمْ مُّصْبِحِيْنَۙ",
			"138" : "وَبِالَّيْلِۗ اَفَلَا تَعْقِلُوْنَ ࣖ ",
			"139" : "وَاِنَّ يُوْنُسَ لَمِنَ الْمُرْسَلِيْنَۗ ",
			"140" : "اِذْ اَبَقَ اِلَى الْفُلْكِ الْمَشْحُوْنِۙ",
			"141" : "فَسَاهَمَ فَكَانَ مِنَ الْمُدْحَضِيْنَۚ",
			"142" : "فَالْتَقَمَهُ الْحُوْتُ وَهُوَ مُلِيْمٌ ",
			"143" : "فَلَوْلَآ اَنَّهٗ كَانَ مِنَ الْمُسَبِّحِيْنَ ۙ",
			"144" : "لَلَبِثَ فِيْ بَطْنِهٖٓ اِلٰى يَوْمِ يُبْعَثُوْنَۚ ",
			"145" : "۞ فَنَبَذْنٰهُ بِالْعَرَاۤءِ وَهُوَ سَقِيْمٌ ۚ ",
			"146" : "وَاَنْۢبَتْنَا عَلَيْهِ شَجَرَةً مِّنْ يَّقْطِيْنٍۚ ",
			"147" : "وَاَرْسَلْنٰهُ اِلٰى مِائَةِ اَلْفٍ اَوْ يَزِيْدُوْنَۚ ",
			"148" : "فَاٰمَنُوْا فَمَتَّعْنٰهُمْ اِلٰى حِيْنٍ",
			"149" : "فَاسْتَفْتِهِمْ اَلِرَبِّكَ الْبَنَاتُ وَلَهُمُ الْبَنُوْنَۚ ",
			"150" : "اَمْ خَلَقْنَا الْمَلٰۤىِٕكَةَ اِنَاثًا وَّهُمْ شٰهِدُوْنَ",
			"151" : "اَلَآ اِنَّهُمْ مِّنْ اِفْكِهِمْ لَيَقُوْلُوْنَۙ",
			"152" : "وَلَدَ اللّٰهُ ۙوَاِنَّهُمْ لَكٰذِبُوْنَۙ",
			"153" : "اَصْطَفَى الْبَنَاتِ عَلَى الْبَنِيْنَۗ ",
			"154" : "مَا لَكُمْۗ  كَيْفَ تَحْكُمُوْنَ",
			"155" : "اَفَلَا تَذَكَّرُوْنَۚ ",
			"156" : "اَمْ لَكُمْ سُلْطٰنٌ مُّبِيْنٌۙ",
			"157" : "فَأْتُوْا بِكِتٰبِكُمْ اِنْ كُنْتُمْ صٰدِقِيْنَ",
			"158" : "وَجَعَلُوْا بَيْنَهٗ وَبَيْنَ الْجِنَّةِ نَسَبًا ۗوَلَقَدْ عَلِمَتِ الْجِنَّةُ اِنَّهُمْ لَمُحْضَرُوْنَۙ",
			"159" : "سُبْحٰنَ اللّٰهِ عَمَّا يَصِفُوْنَۙ",
			"160" : "اِلَّا عِبَادَ اللّٰهِ الْمُخْلَصِيْنَ",
			"161" : "فَاِنَّكُمْ وَمَا تَعْبُدُوْنَۙ",
			"162" : "مَآ اَنْتُمْ عَلَيْهِ بِفٰتِنِيْنَۙ",
			"163" : "اِلَّا مَنْ هُوَ صَالِ الْجَحِيْمِ",
			"164" : "وَمَا مِنَّآ اِلَّا لَهٗ مَقَامٌ مَّعْلُوْمٌۙ",
			"165" : "وَّاِنَّا لَنَحْنُ الصَّۤافُّوْنَۖ",
			"166" : "وَاِنَّا لَنَحْنُ الْمُسَبِّحُوْنَ",
			"167" : "وَاِنْ كَانُوْا لَيَقُوْلُوْنَۙ",
			"168" : "لَوْ اَنَّ عِنْدَنَا ذِكْرًا مِّنَ الْاَوَّلِيْنَۙ",
			"169" : "لَكُنَّا عِبَادَ اللّٰهِ الْمُخْلَصِيْنَ",
			"170" : "فَكَفَرُوْا بِهٖۚ فَسَوْفَ يَعْلَمُوْنَ",
			"171" : "وَلَقَدْ سَبَقَتْ كَلِمَتُنَا لِعِبَادِنَا الْمُرْسَلِيْنَ ۖ",
			"172" : "اِنَّهُمْ لَهُمُ الْمَنْصُوْرُوْنَۖ",
			"173" : "وَاِنَّ جُنْدَنَا لَهُمُ الْغٰلِبُوْنَ",
			"174" : "فَتَوَلَّ عَنْهُمْ حَتّٰى حِيْنٍۙ",
			"175" : "وَّاَبْصِرْهُمْۗ فَسَوْفَ يُبْصِرُوْنَ",
			"176" : "اَفَبِعَذَابِنَا يَسْتَعْجِلُوْنَ",
			"177" : "فَاِذَا نَزَلَ بِسَاحَتِهِمْ فَسَاۤءَ صَبَاحُ الْمُنْذَرِيْنَ",
			"178" : "وَتَوَلَّ عَنْهُمْ حَتّٰى حِيْنٍۙ",
			"179" : "وَّاَبْصِرْۗ فَسَوْفَ يُبْصِرُوْنَ",
			"180" : "سُبْحٰنَ رَبِّكَ رَبِّ الْعِزَّةِ عَمَّا يَصِفُوْنَۚ",
			"181" : "وَسَلٰمٌ عَلَى الْمُرْسَلِيْنَۚ ",
			"182" : "وَالْحَمْدُ لِلّٰهِ رَبِّ الْعٰلَمِيْنَ ࣖ"
		},
		"latin" : {
			"1" : "Waṣ-ṣāffāti ṣaffā(n).",
			"2" : "Faz-zājirāti zajrā(n).",
			"3" : "Fat-tāliyāti żikrā(n).",
			"4" : "Inna ilāhakum lawāḥid(un).",
			"5" : "Rabbus-samāwāti wal-arḍi wa mā bainahumā wa rabbul-masyāriq(i).",
			"6" : "Innā zayyannas-samā'ad-dun-yā bizīnatinil-kawākib(i).",
			"7" : "Wa ḥifẓam min kulli syaiṭānim mārid(in).",
			"8" : "Lā yassammā‘ūna ilal-mala'il-a‘lā wa yuqżafūna min kulli jānib(in).",
			"9" : "Duḥūraw wa lahum ‘ażābuw wāṣib(un).",
			"10" : "Illā man khaṭifal-khaṭfata fa'atba‘ahū syihābun ṡāqib(un).",
			"11" : "Fastaftihim ahum asyaddu khalqan am man khalaqnā, innā khalaqnāhum min ṭīnil lāzib(in).",
			"12" : "Bal ‘ajibta wa yaskharūn(a).",
			"13" : "Wa iżā żukkirū lā yażkurūn(a).",
			"14" : "Wa iżā ra'au āyatay yastaskhirūn(a).",
			"15" : "Wa qālū in hāżā illā siḥrum mubīn(un).",
			"16" : "A'iżā mitnā wa kunnā turābaw wa ‘iẓāman a'innā lamab‘ūṡūn(a).",
			"17" : "Awa ābā'unal-awwalūn(a).",
			"18" : "Qul na‘am wa antum dākhirūn(a).",
			"19" : "Fa'innamā hiya zajratuw wāḥidatun fa'iżā hum yanẓurūn(a).",
			"20" : "Wa qālū yā wailanā hāżā yaumud-dīn(i).",
			"21" : "Hāżā yaumul-faṣlil-lażī kuntum bihī tukażżibūn(a).",
			"22" : "Uḥsyurul-lażīna ẓalamū wa azwājahum wa mā kānū ya‘budūn(a).",
			"23" : "Min dūnillāhi fahdūhum ilā ṣirāṭil-jaḥīm(i).",
			"24" : "Waqifūhum innahum mas'ūlūn(a).",
			"25" : "Mā lakum lā tanāṣarūn(a).",
			"26" : "Bal humul-yauma mustaslimūn(a).",
			"27" : "Wa aqbala ba‘ḍuhum ‘alā ba‘ḍiy yatasā'alūn(a).",
			"28" : "Qālū innakum kuntum ta'tūnanā ‘anil-yamīn(i).",
			"29" : "Qālū bal lam takūnū mu'minīn(a).",
			"30" : "Wa mā kāna lanā ‘alaikum min sulṭān(in), bal kuntum qauman ṭāgīn(a).",
			"31" : "Fa ḥaqqa ‘alainā qaulu rabbinā, innā lażā'iqūn(a).",
			"32" : "Fa agwainākum innā kunnā gāwīn(a).",
			"33" : "Fa innahum yauma'iżin fil-‘ażābi musytarikūn(a).",
			"34" : "Innā każālika naf‘alu bil-mujrimīn(a).",
			"35" : "Innahum kānū iżā qīla lahum lā ilāha illallāhu yastakbirūn(a).",
			"36" : "Wa yaqūlūna a'innā latārikū ālihatinā lisyā‘irim majnūn(in).",
			"37" : "Bal jā'a bil-ḥaqqi wa ṣaddaqal-mursalīn(a).",
			"38" : "Innakum lażā'iqul-‘ażābil-alīm(i).",
			"39" : "Wa mā tujzauna illā mā kuntum ta‘malūn(a).",
			"40" : "Illā ‘ibādallāhil-mukhlaṣīn(a).",
			"41" : "Ulā'ika lahum rizqum ma‘lūm(un).",
			"42" : "Fawākihu wa hum mukramūn(a).",
			"43" : "Fī jannātin na‘īm(i).",
			"44" : "‘Alā sururim mutaqābilīn(a).",
			"45" : "Yuṭāfu ‘alaihim bika'sim mim ma‘īn(in).",
			"46" : "Baiḍā'a lażżatil lisy-syāribīn(a).",
			"47" : "Lā fīhā gauluw wa lā hum ‘anhā yunzafūn(a).",
			"48" : "Wa ‘indahum qāṣirātuṭ-ṭarfi ‘īn(un).",
			"49" : "Ka'annahum baiḍum maknūn(un).",
			"50" : "Fa'aqbala ba‘ḍuhum ‘alā ba‘ḍiy yatasā'alūn(a).",
			"51" : "Qāla qā'ilum minhum innī kāna lī qarīn(un).",
			"52" : "Yaqūlu a'innaka laminal-muṣaddiqīn(a).",
			"53" : "A'iżā mitnā wa kunnā turāban a'innā lamadīnūn(a).",
			"54" : "Qāla hal antum muṭṭali‘ūn(a).",
			"55" : "Faṭṭala‘a fa ra'āhu fī sawā'il-jaḥīm(i).",
			"56" : "Qāla tallāhi in kitta laturdīn(i).",
			"57" : "Wa lau lā ni‘matu rabbī lakuntu minal-muḥḍarīn(a).",
			"58" : "Afamā naḥnu bimayyitīn(a).",
			"59" : "Illā mautatunal-ūlā wa mā naḥnu bimu‘ażżabīn(a).",
			"60" : "Inna hāżā lahuwal-fauzul-‘aẓīm(u).",
			"61" : "Limiṡli hāżā falya‘malil-‘āmilūn(a).",
			"62" : "Ażālika khairun nuzulan am syajaratuz-zaqqūm(i).",
			"63" : "Innā ja‘alnāhā fitnatal liẓ-ẓālimīn(a).",
			"64" : "Innahā syajaratun takhruju fī aṣlil-jaḥīm(i).",
			"65" : "Ṭal‘uhā ka'annahū ru'ūsusy-syayāṭīn(i).",
			"66" : "Fa innahum la'ākilūna minhā fa māli'ūna minhal-buṭūn(a).",
			"67" : "Ṡumma inna lahum ‘alaihā lasyaubam min ḥamīm(in).",
			"68" : "Ṡumma inna marji‘ahum la'ilal-jaḥīm(i).",
			"69" : "Innahum alfau ābā'ahum ḍāllīn(a).",
			"70" : "Fahum ‘alā āṡārihim yuhra‘ūn(a).",
			"71" : "Wa laqad ḍalla qablahum akṡarul-awwalīn(a).",
			"72" : "Wa laqad arsalnā fīhim munżirīn(a).",
			"73" : "Fanẓur kaifa kāna ‘āqibatul-munżarīn(a).",
			"74" : "Illā ‘ibādallāhil-mukhlaṣīn(a).",
			"75" : "Wa laqad nādānā nūḥun falani‘mal-mujībūn(a).",
			"76" : "Wa najjaināhu wa ahlahū minal-karbil-‘aẓīm(i).",
			"77" : "Wa ja‘alnā żurriyyatahū humul-bāqīn(a).",
			"78" : "Wa taraknā ‘alaihi fil-ākhirīn(a).",
			"79" : "Salāmun ‘alā nūḥin fil-‘ālamīn(a).",
			"80" : "Innā każālika najzil-muḥsinīn(a).",
			"81" : "Innahū min ‘ibādinal-mu'minīn(a).",
			"82" : "Ṡumma agraqnal-ākharīn(a).",
			"83" : "Wa inna min syī‘atihī la'ibrāhīm(a).",
			"84" : "Iż jā'a rabbahū biqalbin salīm(in).",
			"85" : "Iż qāla li'abīhi wa qaumihī māżā ta‘budūn(a).",
			"86" : "A'ifkan ālihatan dūnallāhi turīdūn(a).",
			"87" : "Famā ẓannukum birabbil-‘ālamīn(a).",
			"88" : "Fa naẓara naẓratan fin-nujūm(i).",
			"89" : "Fa qāla innī saqīm(un).",
			"90" : "Fa tawallau ‘anhu mudbirīn(a).",
			"91" : "Farāga ilā ālihatihim faqāla alā ta'kulūn(a).",
			"92" : "Mā lakum lā tanṭiqūn(a).",
			"93" : "Farāga ‘alaihim ḍarbam bil-yamīn(i).",
			"94" : "Fa aqbalū ilaihi yaziffūn(a).",
			"95" : "Qāla ata‘budūna mā tanḥitūn(a).",
			"96" : "Wallāhu khalaqakum wa mā ta‘malūn(a).",
			"97" : "Qālubnū lahū bun-yānan fa'alqūhu fil-jaḥīm(i).",
			"98" : "Fa arādū bihī kaidan faja‘alnāhumul-asfalīn(a).",
			"99" : "Wa qāla innī żāhibun ilā rabbī sayahdīn(i).",
			"100" : "Rabbi hab lī minaṣ-ṣāliḥīn(a).",
			"101" : "Fa basysyarnāhu bigulāmin ḥalīm(in).",
			"102" : "Falammā balaga ma‘ahus-sa‘ya qāla yā bunayya innī arā fil-manāmi annī ażbaḥuka fanẓur māżā tarā, qāla yā abatif‘al mā tu'mar(u), satajidunī in syā'allāhu minaṣ-ṣābirīn(a).",
			"103" : "Falammā aslamā wa tallahū lil-jabīn(i).",
			"104" : "Wa nādaināhu ay yā ibrāhīm(u).",
			"105" : "Qad ṣaddaqtar-ru'yā, innā każālika najzil-muḥsinīn(a).",
			"106" : "Inna hāżā lahuwal-balā'ul-mubīn(u).",
			"107" : "Wa fadaināhu biżibḥin ‘aẓīm(in).",
			"108" : "Wa taraknā ‘alaihi fil-ākhirīn(a).",
			"109" : "Salāmun ‘alā ibrāhīm(a).",
			"110" : "Każālika najzil-muḥsinīn(a).",
			"111" : "Innahū min ‘ibādinal-mu'minīn(a).",
			"112" : "Wa basysyarnāhu bi'isḥāqa nabiyyam minaṣ-ṣāliḥīn(a).",
			"113" : "Wa bāraknā ‘alaihi wa ‘alā isḥāq(a), wa min żurriyyatihimā muḥsinuw wa ẓālimul linafsihī mubīn(un).",
			"114" : "Wa laqad manannā ‘alā mūsā wa hārūn(a).",
			"115" : "Wa najjaināhumā wa qaumahumā minal-karbil-‘aẓīm(i).",
			"116" : "Wa naṣarnāhum fakānū humul-gālibīn(a).",
			"117" : "Wa ātaināhumal-kitābal-mustabīn(a).",
			"118" : "Wa hadaināhumaṣ-ṣirāṭal-mustaqīm(a).",
			"119" : "Wa taraknā ‘alaihimā fil-ākhirīn(a).",
			"120" : "Salāmun ‘alā mūsā wa hārūn(a).",
			"121" : "Innā każālika najzil-muḥsinīn(a).",
			"122" : "Innahumā min ‘ibādinal-mu'minīn(a).",
			"123" : "Wa inna ilyāsa laminal-mursalīn(a).",
			"124" : "Iż qāla liqaumihī alā tattaqūn(a).",
			"125" : "Atad‘ūna ba‘law wa tażarūna aḥsanal-khāliqīn(a).",
			"126" : "Allāha rabbakum wa rabba ābā'ikumul-awwalīn(a).",
			"127" : "Fakażżabūhu fa'innahum lamuḥḍarūn(a).",
			"128" : "Illā ‘ibādallāhil-mukhlaṣīn(a).",
			"129" : "Wa taraknā ‘alaihi fil-ākhirīn(a).",
			"130" : "Salāmun ‘alā ilyāsīn(a).",
			"131" : "Innā każālika najzil-muḥsinīn(a).",
			"132" : "Innahū min ‘ibādinal-mu'minīn(a).",
			"133" : "Wa inna lūṭal laminal-mursalīn(a).",
			"134" : "Iż najjaināhu wa ahlahū ajma‘īn(a).",
			"135" : "Illā ‘ajūzan fil-gābirīn(a).",
			"136" : "Ṡumma dammarnal-ākharīn(a).",
			"137" : "Wa innakum latamurrūna ‘alaihim muṣbiḥīn(a).",
			"138" : "Wa bil-lail(i), afalā ta‘qilūn(a).",
			"139" : "Wa inna yūnusa laminal-mursalīn(a).",
			"140" : "Iż abaqa ilal-fulkil-masyḥūn(i).",
			"141" : "Fa sāhama fakāna minal-mudḥaḍīn(a).",
			"142" : "Faltaqamahul-ḥūtu wa huwa mulīm(un).",
			"143" : "Falau lā annahū kāna minal-musabbiḥīn(a).",
			"144" : "Lalabiṡa fī baṭnihī ilā yaumi yub‘aṡūn(a).",
			"145" : "Fa nabażnāhu bil-‘arā'i wa huwa saqīm(un).",
			"146" : "Wa ambatnā ‘alaihi syajaratam miy yaqṭīn(in).",
			"147" : "Wa arsalnāhu ilā mi'ati alfin au yazīdūn(a).",
			"148" : "Fa'āmanū famatta‘nāhum ilā ḥīn(in).",
			"149" : "Fastaftihim alirabbikal-banātu wa lahumul-banūn(a).",
			"150" : "Am khalaqnal-malā'ikata ināṡaw wa hum syāhidūn(a).",
			"151" : "Alā innahum min ifkihim layaqūlūn(a).",
			"152" : "Waladallāh(u), wa innahum lakāżibūn(a).",
			"153" : "Aṣṭafal-banāti ‘alal-banīn(a).",
			"154" : "Mā lakum, kaifa taḥkumūn(a).",
			"155" : "Afalā tażakkarūn(a).",
			"156" : "Am lakum sulṭānum mubīn(un).",
			"157" : "Fa'tū bikitābikum in kuntum ṣādiqīn(a).",
			"158" : "Wa ja‘alū bainahū wa bainal-jinnati nasabā(n), wa laqad ‘alimatil-jinnatu innahum lamuḥḍarūn(a).",
			"159" : "Subḥānallāhi ‘ammā yaṣifūn(a).",
			"160" : "Illā ‘ibādallāhil-mukhlaṣīn(a).",
			"161" : "Fa'innakum wa mā ta‘budūn(a).",
			"162" : "Mā antum ‘alaihi bifātinīn(a).",
			"163" : "Illā man huwa ṣālil-jaḥīm(i).",
			"164" : "Wa mā minnā illā lahū maqāmum ma‘lūm(un).",
			"165" : "Wa innā lanaḥnuṣ-ṣāffūn(a).",
			"166" : "Wa innā lanaḥnul-musabbiḥūn(a).",
			"167" : "Wa in kānū layaqūlūn(a).",
			"168" : "Lau anna ‘indanā żikram minal-awwalīn(a).",
			"169" : "Lakunnā ‘ibādallāhil-mukhlaṣīn(a).",
			"170" : "Fa kafarū bih(ī), fasaufa ya‘lamūn(a).",
			"171" : "Wa laqad sabaqat kalimatunā li‘ibādinal-mursalīn(a).",
			"172" : "Innahum lahumul-manṣūrūn(a).",
			"173" : "Wa inna jundanā lahumul-gālibūn(a).",
			"174" : "Fatawalla ‘anhum ḥattā ḥīn(in).",
			"175" : "Wa abṣirhum, fa saufa yubṣirūn(a).",
			"176" : "Afabi‘ażābinā yasta‘jilūn(a).",
			"177" : "Fa iżā nazala bisāḥatihim fa sā'a ṣabāḥul-munżarīn(a).",
			"178" : "Wa tawalla ‘anhum ḥattā ḥīn(in).",
			"179" : "Wa abṣir, fasaufa yubṣirūn(a).",
			"180" : "Subḥāna rabbika rabbil-‘izzati ‘ammā yaṣifūn(a).",
			"181" : "Wa salāmun ‘alal-mursalīn(a).",
			"182" : "Wal-ḥamdu lillāhi rabbil-‘ālamīn(a)."
		},
		"terjemah" : {
			"1" : "Demi (rombongan malaikat) yang berbaris bersaf-saf, (untuk beribadah kepada Allah),",
			"2" : "demi (rombongan malaikat) yang mencegah (segala sesuatu) dengan sungguh-sungguh,",
			"3" : "demi (rombongan malaikat) yang membacakan peringatan,",
			"4" : "sungguh, Tuhanmu benar-benar Esa.",
			"5" : "Tuhan langit dan bumi dan apa yang berada di antara keduanya dan Tuhan tempat-tempat terbitnya matahari.",
			"6" : "Sesungguhnya Kami telah menghiasi langit dunia (yang terdekat) dengan hiasan (berupa) bintang-bintang.",
			"7" : "(Kami telah menjaganya dengan) penjagaan yang sempurna dari setiap setan yang durhaka.",
			"8" : "Mereka (setan-setan) tidak dapat mendengar (percakapan) para malaikat dan mereka dilempari dari segala penjuru",
			"9" : "untuk mengusir mereka. Bagi mereka azab yang kekal (di akhirat),",
			"10" : "kecuali (setan) yang menyambar pembicaraan dengan sekali sambar; maka ia dikejar oleh bintang yang menyala.",
			"11" : "Maka, tanyakanlah kepada mereka (musyrik Makkah), \u201cApakah mereka (manusia) lebih sulit penciptaannya ataukah selainnya (langit, bumi, dan lainnya) yang telah Kami ciptakan?\u201d Sesungguhnya Kami telah menciptakan (bapak) mereka (Adam) dari tanah liat.",
			"12" : "Bahkan, engkau (Nabi Muhammad) menjadi heran (terhadap keingkaran mereka) dan mereka selalu menghinamu.",
			"13" : "Apabila diberi peringatan, mereka tidak mengingat (mengindahkannya).",
			"14" : "Apabila melihat suatu tanda (kebesaran Allah atau kebenaran Nabi Muhammad), mereka sangat menghina.",
			"15" : "Mereka berkata, \u201cIni tidak lain hanyalah sihir yang nyata.",
			"16" : "Apabila kami telah mati, (lalu) menjadi tanah dan tulang-belulang, apakah kami benar-benar akan dibangkitkan?",
			"17" : "Apakah nenek moyang kami yang terdahulu (akan dibangkitkan pula)?\u201d",
			"18" : "Katakanlah (Nabi Muhammad), \u201cYa (kamu akan dibangkitkan) dan kamu akan terhina.\u201d",
			"19" : "Sesungguhnya kebangkitan itu hanya dengan satu teriakan (tiupan sangkakala kedua). Maka, seketika itu mereka (bangun dari kematiannya) melihat (apa yang terjadi).",
			"20" : "Mereka berkata, \u201cAlangkah celaka kami! (Kiranya) inilah hari Pembalasan itu.\u201d",
			"21" : "Inilah hari keputusan yang dahulu (selalu) kamu dustakan.",
			"22" : "(Lalu, diperintahkan kepada para malaikat,) \u201cKumpulkanlah orang-orang yang zalim beserta teman sejawat mereka dan apa yang dahulu mereka sembah",
			"23" : "selain Allah. Lalu, tunjukkanlah kepada mereka jalan ke (neraka) Jahim.",
			"24" : "Tahanlah mereka (di tempat perhentian). Sesungguhnya mereka akan ditanya (tentang keyakinan dan perilaku mereka).\u201d",
			"25" : "(Mereka lalu dikecam,) \u201cMengapa kamu tidak tolong-menolong (sebagaimana kamu di dunia)?\u201d",
			"26" : "Bahkan, mereka pada hari itu menyerah (kepada putusan Allah).",
			"27" : "Sebagian mereka menghadap kepada sebagian yang lain saling bertanya (berbantah-bantahan).",
			"28" : "(Pengikut) mereka berkata (kepada pemimpinnya), \u201cSesungguhnya kamulah yang dahulu selalu mendatangi kami dari arah kanan (untuk menghalangi kami dari kebajikan).\u201d",
			"29" : "(Pemimpin) mereka menjawab, \u201c(Tidak,) bahkan kamulah yang tidak (mau) menjadi orang mukmin.",
			"30" : "(Sebenarnya,) kami sedikit pun tidak berkuasa terhadapmu (untuk menghalang-halangimu), bahkan kamulah kaum yang melampaui batas.",
			"31" : "Maka, putusan (azab) Tuhan (akan) benar-benar menimpa kita. Pasti kita akan merasakan (azab itu).",
			"32" : "Kami (mengakui) telah menyesatkan kamu. Sesungguhnya kami sendiri orang-orang yang sesat.\u201d",
			"33" : "Sesungguhnya mereka pada hari itu bersama-sama merasakan azab.",
			"34" : "Sesungguhnya demikianlah Kami memperlakukan orang-orang yang berbuat dosa.",
			"35" : "Sesungguhnya dahulu apabila dikatakan kepada mereka, \u201cL\u0101 il\u0101ha illall\u0101h\u201d (Tidak ada tuhan selain Allah), mereka menyombongkan diri.",
			"36" : "Mereka berkata, \u201cApakah kami harus meninggalkan sesembahan kami karena seorang penyair gila?\u201d",
			"37" : "Padahal dia (Nabi Muhammad) datang dengan membawa kebenaran dan membenarkan para rasul (sebelumnya).",
			"38" : "Sesungguhnya kamu pasti akan merasakan azab yang pedih.",
			"39" : "Kamu tidak diberi balasan, kecuali terhadap apa yang telah kamu kerjakan.",
			"40" : "Akan tetapi, hamba-hamba Allah yang terpilih (karena keikhlasannya),",
			"41" : "mereka itu memperoleh rezeki yang sudah ditentukan,",
			"42" : "(yaitu) buah-buahan. Mereka adalah orang-orang yang dimuliakan",
			"43" : "di dalam surga-surga yang penuh kenikmatan.",
			"44" : "(Mereka duduk) berhadap-hadapan di atas dipan-dipan.",
			"45" : "Kepada mereka diedarkan gelas (yang berisi minuman) dari mata air (surga).",
			"46" : "(Warnanya) putih bersih dan lezat rasanya bagi orang-orang yang meminum(-nya).",
			"47" : "Tidak ada di dalamnya (unsur) yang membahayakan dan mereka tidak mabuk karenanya.",
			"48" : "Di sisi mereka ada (bidadari-bidadari) yang bermata indah dan membatasi pandangannya (dari selain pasangan mereka).",
			"49" : "(Warna kulit) mereka seperti (warna) telur yang tersimpan dengan baik.",
			"50" : "Mereka berhadap-hadapan satu sama lain sambil bercakap-cakap.",
			"51" : "Berkatalah salah seorang di antara mereka, \u201cSesungguhnya aku dahulu (di dunia) pernah mempunyai seorang teman",
			"52" : "yang berkata, \u2018Apakah sesungguhnya kamu termasuk orang-orang yang membenarkan (hari Kebangkitan)?",
			"53" : "Apabila kami telah mati (lalu) menjadi tanah dan tulang-belulang, apakah kami benar-benar (akan dibangkitkan untuk) diberi balasan?\u2019\u201d",
			"54" : "Dia berkata, \u201cMaukah kamu menengok (temanku itu)?\u201d",
			"55" : "Maka, dia menengoknya. Lalu, dia melihat (teman)-nya itu di tengah-tengah (neraka) Jahim.",
			"56" : "Dia berkata, \u201cDemi Allah, engkau hampir saja mencelakakanku.",
			"57" : "Sekiranya bukan karena nikmat Tuhanku, pastilah aku termasuk orang-orang yang diseret (ke neraka).",
			"58" : "Apakah kita tidak akan mati,",
			"59" : "kecuali kematian kita yang pertama saja (di dunia) dan kita tidak akan diazab (di akhirat ini)?\u201d",
			"60" : "Sesungguhnya ini benar-benar kemenangan yang agung.",
			"61" : "Untuk (kemenangan) seperti ini, hendaklah beramal (di dunia) orang-orang yang mampu beramal.",
			"62" : "Apakah (makanan surga) itu hidangan yang lebih baik ataukah pohon zaqum?",
			"63" : "Sesungguhnya Kami menjadikannya (pohon zaqum itu) sebagai azab bagi orang-orang zalim.",
			"64" : "Sesungguhnya itu adalah pohon yang keluar dari dasar (neraka) Jahim.",
			"65" : "Mayangnya seperti kepala-kepala setan.",
			"66" : "Sesungguhnya mereka benar-benar memakan sebagian darinya (buah pohon itu) dan mereka memenuhi perutnya dengan buahnya (zaqum).",
			"67" : "(Setelah makan buah zaqum,) sesungguhnya bagi mereka minuman yang dicampur dengan air yang sangat panas.",
			"68" : "Kemudian, tempat kembali mereka pasti ke (neraka) Jahim.",
			"69" : "Sesungguhnya mereka mendapati nenek moyang mereka dalam keadaan sesat.",
			"70" : "Mereka tergesa-gesa mengikuti jejak (nenek moyang) mereka.",
			"71" : "Sungguh, sebelum mereka (kaum Quraisy), benar-benar telah sesat sebagian besar dari orang-orang yang dahulu.",
			"72" : "Sungguh, Kami benar-benar telah mengutus (rasul) pemberi peringatan di kalangan mereka.",
			"73" : "Maka, perhatikanlah bagaimana kesudahan orang-orang yang diberi peringatan itu,",
			"74" : "kecuali hamba-hamba Allah yang terpilih (karena keikhlasannya).",
			"75" : "Sungguh, Nuh benar-benar telah berdoa kepada Kami dan sungguh, Kamilah sebaik-baik yang memperkenankan doa.",
			"76" : "Kami telah menyelamatkan dia dan pengikutnya dari bencana yang besar.",
			"77" : "Kami menjadikan keturunannya orang-orang yang bertahan (di bumi).",
			"78" : "Kami mengabadikan untuknya (pujian) pada orang-orang yang datang kemudian,",
			"79" : "\u201cKesejahteraan (Kami limpahkan) atas Nuh di semesta alam.\u201d",
			"80" : "Sesungguhnya, demikianlah Kami memberi balasan kepada orang-orang yang berbuat kebaikan.",
			"81" : "Sesungguhnya dia termasuk hamba-hamba Kami yang mukmin.",
			"82" : "Kemudian, Kami menenggelamkan yang lain.",
			"83" : "Sesungguhnya Ibrahim termasuk golongannya (Nuh).646)",
			"84" : "(Ingatlah) ketika dia datang kepada Tuhannya dengan hati yang suci,647)",
			"85" : "ketika dia berkata kepada ayahnya dan kaumnya, \u201cApa yang kamu sembah itu?",
			"86" : "Apakah kamu menghendaki kebohongan dengan sesembahan selain Allah?",
			"87" : "Maka, bagaimana anggapanmu terhadap Tuhan semesta alam?\u201d",
			"88" : "Lalu, dia (Ibrahim) memandang sekilas ke arah bintang-bintang,",
			"89" : "kemudian dia berkata, \u201cSesungguhnya aku sakit.\u201d",
			"90" : "Mereka lalu berpaling darinya seraya meninggalkannya.",
			"91" : "Kemudian, dia langsung menuju ke berhala-berhala mereka (secara diam-diam), lalu berkata, \u201cMengapa kamu tidak makan?648)",
			"92" : "Mengapa kamu tidak menjawab?\u201d",
			"93" : "Dia lalu menghadap ke (berhala-berhala) itu sambil memukul dengan tangan kanan(-nya).",
			"94" : "Kemudian, mereka (kaumnya) datang bergegas kepadanya.",
			"95" : "Dia (Ibrahim) berkata, \u201cApakah kamu menyembah patung-patung yang kamu pahat itu?",
			"96" : "Padahal Allahlah yang menciptakanmu dan apa yang kamu perbuat itu.\u201d",
			"97" : "Mereka berkata, \u201cBuatlah bangunan (perapian) untuk (membakar)-nya, lalu lemparkan dia ke dalam api yang menyala-nyala itu.\u201d",
			"98" : "Mereka bermaksud memperdayainya, (namun Allah menyelamatkannya), lalu Kami menjadikan mereka orang-orang yang hina.",
			"99" : "Dia (Ibrahim) berkata, \u201cSesungguhnya aku akan pergi (menghadap) kepada Tuhanku.649) Dia akan memberiku petunjuk.\u201d",
			"100" : "100. (Ibrahim berdoa,) \u201cYa Tuhanku, anugerahkanlah kepadaku (keturunan) yang termasuk orang-orang saleh.\u201d",
			"101" : "Maka, Kami memberi kabar gembira kepadanya dengan (kelahiran) seorang anak (Ismail) yang sangat santun.",
			"102" : "Ketika anak itu sampai pada (umur) ia sanggup bekerja bersamanya, ia (Ibrahim) berkata, \u201cWahai anakku, sesungguhnya aku bermimpi bahwa aku menyembelihmu. Pikirkanlah apa pendapatmu?\u201d Dia (Ismail) menjawab, \u201cWahai ayahku, lakukanlah apa yang diperintahkan (Allah) kepadamu! Insyaallah engkau akan mendapatiku termasuk orang-orang sabar.\u201d",
			"103" : "Ketika keduanya telah berserah diri dan dia (Ibrahim) meletakkan pelipis anaknya di atas gundukan (untuk melaksanakan perintah Allah),",
			"104" : "Kami memanggil dia, \u201cWahai Ibrahim,",
			"105" : "sungguh, engkau telah membenarkan mimpi itu.\u201d Sesungguhnya demikianlah Kami memberi balasan kepada orang-orang yang berbuat kebaikan.",
			"106" : "Sesungguhnya ini benar-benar suatu ujian yang nyata.",
			"107" : "Kami menebusnya dengan seekor (hewan) sembelihan yang besar.650)",
			"108" : "Kami mengabadikan untuknya (pujian) pada orang-orang yang datang kemudian,",
			"109" : "\u201cSalam sejahtera atas Ibrahim.\u201d",
			"110" : "Demikianlah Kami memberi balasan kepada orang-orang yang berbuat kebaikan.",
			"111" : "Sesungguhnya dia termasuk hamba-hamba Kami yang mukmin.",
			"112" : "Kami telah memberinya kabar gembira tentang (akan dilahirkannya) Ishaq, seorang nabi yang termasuk orang-orang saleh.",
			"113" : "Kami melimpahkan keberkahan kepadanya dan Ishaq. Sebagian keturunan keduanya ada yang berbuat baik dan ada (pula) yang terang-terangan berbuat zalim terhadap dirinya sendiri.",
			"114" : "Sungguh, Kami benar-benar telah melimpahkan nikmat kepada Musa dan Harun.",
			"115" : "Kami telah menyelamatkan keduanya dan kaumnya dari bencana yang besar.",
			"116" : "Kami telah menolong mereka sehingga mereka menjadi orang-orang yang menang.",
			"117" : "Kami telah menganugerahkan kepada keduanya Kitab yang sangat jelas (Taurat).",
			"118" : "Kami telah membimbing keduanya ke jalan yang lurus.",
			"119" : "Kami telah mengabadikan untuk keduanya (pujian) pada orang-orang yang datang kemudian,",
			"120" : "\u201cSalam sejahtera atas Musa dan Harun.\u201d",
			"121" : "Sesungguhnya, demikianlah Kami memberi balasan kepada orang-orang yang berbuat kebaikan.",
			"122" : "Sesungguhnya keduanya termasuk hamba-hamba Kami yang mukmin.",
			"123" : "Sesungguhnya Ilyas benar-benar termasuk para rasul.",
			"124" : "(Ingatlah) ketika dia berkata kepada kaumnya, \u201cMengapa kamu tidak bertakwa?",
			"125" : "Apakah kamu terus menyeru Ba\u2018l651) dan meninggalkan sebaik-baik pencipta,",
			"126" : "Allah Tuhanmu dan Tuhan nenek moyangmu yang terdahulu?\u201d",
			"127" : "Mereka kemudian mendustakannya (Ilyas). Sesungguhnya mereka akan diseret (ke neraka),",
			"128" : "kecuali hamba-hamba Allah yang terpilih (karena keikhlasannya).",
			"129" : "Kami mengabadikan untuknya (pujian) pada orang-orang yang datang kemudian,",
			"130" : "\u201cSalam sejahtera atas Ilyas dan kaumnya.\u201d",
			"131" : "Sesungguhnya, demikianlah Kami memberi balasan kepada orang-orang yang berbuat kebaikan.",
			"132" : "Sesungguhnya dia termasuk hamba-hamba Kami yang mukmin.",
			"133" : "Sesungguhnya Lut benar-benar termasuk para rasul.",
			"134" : "(Ingatlah) ketika Kami telah menyelamatkan dia dan pengikutnya semua,",
			"135" : "kecuali seorang perempuan tua (istrinya) yang termasuk golongan (orang-orang kafir) yang tertinggal.",
			"136" : "Kemudian, Kami binasakan yang lain.652)",
			"137" : "Sesungguhnya kamu (penduduk Makkah) benar-benar akan melintasi (bekas-bekas kehancuran) mereka pada waktu pagi",
			"138" : "dan waktu malam. Mengapa kamu tidak mengerti?",
			"139" : "Sesungguhnya Yunus benar-benar termasuk para rasul.",
			"140" : "(Ingatlah) ketika dia berlari ke kapal yang penuh muatan,",
			"141" : "kemudian dia ikut diundi,653) maka dia termasuk orang-orang yang kalah (dalam undian).",
			"142" : "Dia kemudian ditelan oleh ikan besar dalam keadaan tercela.654)",
			"143" : "Seandainya dia bukan golongan orang yang banyak bertasbih kepada Allah,",
			"144" : "niscaya dia akan tetap tinggal di perutnya (ikan) sampai hari Kebangkitan.",
			"145" : "Kami kemudian melemparkannya (dari mulut ikan) ke daratan yang tandus, sedang dia dalam keadaan sakit.",
			"146" : "Kami kemudian menumbuhkan tanaman sejenis labu untuknya.",
			"147" : "Kami mengutusnya kepada seratus ribu (orang) atau lebih,",
			"148" : "lalu mereka beriman. Maka, Kami menganugerahkan kenikmatan hidup kepada mereka hingga waktu tertentu.",
			"149" : "(Wahai Nabi Muhammad,) tanyalah mereka (orang-orang kafir Makkah), \u201cApakah untuk Tuhanmu anak-anak perempuan, sedangkan untuk mereka anak-anak laki-laki655)",
			"150" : "atau Kami menciptakan malaikat-malaikat berupa perempuan, sedangkan mereka menyaksikan(-nya)?\u201d",
			"151" : "Ingatlah, sesungguhnya mereka benar-benar mengatakan dengan kebohongan mereka,",
			"152" : "\u201cAllah mempunyai anak.\u201d Sesungguhnya mereka benar-benar pendusta.",
			"153" : "Apakah Dia (Allah) lebih memilih anak-anak perempuan daripada anak-anak laki-laki?",
			"154" : "Apa yang telah terjadi pada kamu? Bagaimana kamu menetapkan(-nya)?",
			"155" : "Maka, mengapa kamu tidak mengambil pelajaran?",
			"156" : "Ataukah kamu mempunyai bukti yang jelas?",
			"157" : "(Kalau begitu,) bawalah kitabmu jika kamu orang-orang yang benar.",
			"158" : "Mereka menjadikan (hubungan) nasab antara Dia dan jin. Sungguh, jin benar-benar telah mengetahui bahwa mereka (kaum musyrik) pasti akan diseret (ke neraka),",
			"159" : "Maha Suci Allah dari apa yang mereka sifatkan,",
			"160" : "kecuali hamba-hamba Allah yang terpilih (karena keikhlasannya).",
			"161" : "Maka, sesungguhnya kamu dan apa yang kamu sembah itu",
			"162" : "tidak akan dapat menyesatkan (seseorang) terhadap Allah,",
			"163" : "kecuali orang yang akan masuk ke (neraka) Jahim.",
			"164" : "(Malaikat berkata,) \u201cTidak satu pun di antara kami, kecuali masing-masing mempunyai kedudukan tertentu.",
			"165" : "Sesungguhnya kamilah yang selalu teratur dalam barisan (dalam melaksanakan perintah Allah).",
			"166" : "Sesungguhnya kamilah yang benar-benar terus bertasbih (kepada Allah).\u201d",
			"167" : "Sesungguhnya mereka (orang kafir Makkah) benar-benar berkata,",
			"168" : "\u201cSeandainya di sisi kami ada sebuah kitab dari (kitab-kitab yang diturunkan) kepada orang-orang terdahulu,",
			"169" : "niscaya kami akan menjadi hamba-hamba Allah yang terpilih.",
			"170" : "Akan tetapi, ternyata mereka mengingkarinya (Al-Qur\u2019an). Maka, kelak mereka akan mengetahui (akibat keingkarannya itu).",
			"171" : "Sungguh, janji Kami benar-benar telah tetap bagi hamba-hamba Kami yang menjadi rasul.",
			"172" : "Sesungguhnya merekalah yang pasti akan mendapat pertolongan,",
			"173" : "dan sesungguhnya bala tentara Kami itulah yang pasti menang.",
			"174" : "Maka, berpalinglah engkau (Nabi Muhammad) dari mereka sampai waktu tertentu!",
			"175" : "Lihatlah mereka! Maka, kelak mereka akan melihat (azab itu).",
			"176" : "Maka, apakah mereka meminta agar azab Kami disegerakan?",
			"177" : "Apabila turun (siksaan itu) di halaman mereka, sangat buruklah pagi hari bagi orang-orang yang diperingatkan itu.",
			"178" : "Berpalinglah engkau (Nabi Muhammad) dari mereka sampai waktu tertentu.",
			"179" : "Lihatlah (mereka)! Maka, kelak mereka akan melihat (azab itu).",
			"180" : "Maha Suci Tuhanmu, Tuhan pemilik kemuliaan dari apa yang mereka sifatkan.",
			"181" : "Selamat sejahtera bagi para rasul.",
			"182" : "Segala puji bagi Allah, Tuhan semesta alam."
		},
		"id_tafsir" : {
			"1" : "3789",
			"2" : "3790",
			"3" : "3791",
			"4" : "3792",
			"5" : "3793",
			"6" : "3794",
			"7" : "3795",
			"8" : "3796",
			"9" : "3797",
			"10" : "3798",
			"11" : "3799",
			"12" : "3800",
			"13" : "3801",
			"14" : "3802",
			"15" : "3803",
			"16" : "3804",
			"17" : "3805",
			"18" : "3806",
			"19" : "3807",
			"20" : "3808",
			"21" : "3809",
			"22" : "3810",
			"23" : "3811",
			"24" : "3812",
			"25" : "3813",
			"26" : "3814",
			"27" : "3815",
			"28" : "3816",
			"29" : "3817",
			"30" : "3818",
			"31" : "3819",
			"32" : "3820",
			"33" : "3821",
			"34" : "3822",
			"35" : "3823",
			"36" : "3824",
			"37" : "3825",
			"38" : "3826",
			"39" : "3827",
			"40" : "3828",
			"41" : "3829",
			"42" : "3830",
			"43" : "3831",
			"44" : "3832",
			"45" : "3833",
			"46" : "3834",
			"47" : "3835",
			"48" : "3836",
			"49" : "3837",
			"50" : "3838",
			"51" : "3839",
			"52" : "3840",
			"53" : "3841",
			"54" : "3842",
			"55" : "3843",
			"56" : "3844",
			"57" : "3845",
			"58" : "3846",
			"59" : "3847",
			"60" : "3848",
			"61" : "3849",
			"62" : "3850",
			"63" : "3851",
			"64" : "3852",
			"65" : "3853",
			"66" : "3854",
			"67" : "3855",
			"68" : "3856",
			"69" : "3857",
			"70" : "3858",
			"71" : "3859",
			"72" : "3860",
			"73" : "3861",
			"74" : "3862",
			"75" : "3863",
			"76" : "3864",
			"77" : "3865",
			"78" : "3866",
			"79" : "3867",
			"80" : "3868",
			"81" : "3869",
			"82" : "3870",
			"83" : "3871",
			"84" : "3872",
			"85" : "3873",
			"86" : "3874",
			"87" : "3875",
			"88" : "3876",
			"89" : "3877",
			"90" : "3878",
			"91" : "3879",
			"92" : "3880",
			"93" : "3881",
			"94" : "3882",
			"95" : "3883",
			"96" : "3884",
			"97" : "3885",
			"98" : "3886",
			"99" : "3887",
			"100" : "3888",
			"101" : "3889",
			"102" : "3890",
			"103" : "3891",
			"104" : "3892",
			"105" : "3893",
			"106" : "3894",
			"107" : "3895",
			"108" : "3896",
			"109" : "3897",
			"110" : "3898",
			"111" : "3899",
			"112" : "3900",
			"113" : "3901",
			"114" : "3902",
			"115" : "3903",
			"116" : "3904",
			"117" : "3905",
			"118" : "3906",
			"119" : "3907",
			"120" : "3908",
			"121" : "3909",
			"122" : "3910",
			"123" : "3911",
			"124" : "3912",
			"125" : "3913",
			"126" : "3914",
			"127" : "3915",
			"128" : "3916",
			"129" : "3917",
			"130" : "3918",
			"131" : "3919",
			"132" : "3920",
			"133" : "3921",
			"134" : "3922",
			"135" : "3923",
			"136" : "3924",
			"137" : "3925",
			"138" : "3926",
			"139" : "3927",
			"140" : "3928",
			"141" : "3929",
			"142" : "3930",
			"143" : "3931",
			"144" : "3932",
			"145" : "3933",
			"146" : "3934",
			"147" : "3935",
			"148" : "3936",
			"149" : "3937",
			"150" : "3938",
			"151" : "3939",
			"152" : "3940",
			"153" : "3941",
			"154" : "3942",
			"155" : "3943",
			"156" : "3944",
			"157" : "3945",
			"158" : "3946",
			"159" : "3947",
			"160" : "3948",
			"161" : "3949",
			"162" : "3950",
			"163" : "3951",
			"164" : "3952",
			"165" : "3953",
			"166" : "3954",
			"167" : "3955",
			"168" : "3956",
			"169" : "3957",
			"170" : "3958",
			"171" : "3959",
			"172" : "3960",
			"173" : "3961",
			"174" : "3962",
			"175" : "3963",
			"176" : "3964",
			"177" : "3965",
			"178" : "3966",
			"179" : "3967",
			"180" : "3968",
			"181" : "3969",
			"182" : "3970"
		},
		"page_juz" : {
			"1" : {"page" : "446", "juz" : "23"},
			"2" : {"page" : "446", "juz" : "23"},
			"3" : {"page" : "446", "juz" : "23"},
			"4" : {"page" : "446", "juz" : "23"},
			"5" : {"page" : "446", "juz" : "23"},
			"6" : {"page" : "446", "juz" : "23"},
			"7" : {"page" : "446", "juz" : "23"},
			"8" : {"page" : "446", "juz" : "23"},
			"9" : {"page" : "446", "juz" : "23"},
			"10" : {"page" : "446", "juz" : "23"},
			"11" : {"page" : "446", "juz" : "23"},
			"12" : {"page" : "446", "juz" : "23"},
			"13" : {"page" : "446", "juz" : "23"},
			"14" : {"page" : "446", "juz" : "23"},
			"15" : {"page" : "446", "juz" : "23"},
			"16" : {"page" : "446", "juz" : "23"},
			"17" : {"page" : "446", "juz" : "23"},
			"18" : {"page" : "446", "juz" : "23"},
			"19" : {"page" : "446", "juz" : "23"},
			"20" : {"page" : "446", "juz" : "23"},
			"21" : {"page" : "446", "juz" : "23"},
			"22" : {"page" : "446", "juz" : "23"},
			"23" : {"page" : "446", "juz" : "23"},
			"24" : {"page" : "446", "juz" : "23"},
			"25" : {"page" : "447", "juz" : "23"},
			"26" : {"page" : "447", "juz" : "23"},
			"27" : {"page" : "447", "juz" : "23"},
			"28" : {"page" : "447", "juz" : "23"},
			"29" : {"page" : "447", "juz" : "23"},
			"30" : {"page" : "447", "juz" : "23"},
			"31" : {"page" : "447", "juz" : "23"},
			"32" : {"page" : "447", "juz" : "23"},
			"33" : {"page" : "447", "juz" : "23"},
			"34" : {"page" : "447", "juz" : "23"},
			"35" : {"page" : "447", "juz" : "23"},
			"36" : {"page" : "447", "juz" : "23"},
			"37" : {"page" : "447", "juz" : "23"},
			"38" : {"page" : "447", "juz" : "23"},
			"39" : {"page" : "447", "juz" : "23"},
			"40" : {"page" : "447", "juz" : "23"},
			"41" : {"page" : "447", "juz" : "23"},
			"42" : {"page" : "447", "juz" : "23"},
			"43" : {"page" : "447", "juz" : "23"},
			"44" : {"page" : "447", "juz" : "23"},
			"45" : {"page" : "447", "juz" : "23"},
			"46" : {"page" : "447", "juz" : "23"},
			"47" : {"page" : "447", "juz" : "23"},
			"48" : {"page" : "447", "juz" : "23"},
			"49" : {"page" : "447", "juz" : "23"},
			"50" : {"page" : "447", "juz" : "23"},
			"51" : {"page" : "447", "juz" : "23"},
			"52" : {"page" : "448", "juz" : "23"},
			"53" : {"page" : "448", "juz" : "23"},
			"54" : {"page" : "448", "juz" : "23"},
			"55" : {"page" : "448", "juz" : "23"},
			"56" : {"page" : "448", "juz" : "23"},
			"57" : {"page" : "448", "juz" : "23"},
			"58" : {"page" : "448", "juz" : "23"},
			"59" : {"page" : "448", "juz" : "23"},
			"60" : {"page" : "448", "juz" : "23"},
			"61" : {"page" : "448", "juz" : "23"},
			"62" : {"page" : "448", "juz" : "23"},
			"63" : {"page" : "448", "juz" : "23"},
			"64" : {"page" : "448", "juz" : "23"},
			"65" : {"page" : "448", "juz" : "23"},
			"66" : {"page" : "448", "juz" : "23"},
			"67" : {"page" : "448", "juz" : "23"},
			"68" : {"page" : "448", "juz" : "23"},
			"69" : {"page" : "448", "juz" : "23"},
			"70" : {"page" : "448", "juz" : "23"},
			"71" : {"page" : "448", "juz" : "23"},
			"72" : {"page" : "448", "juz" : "23"},
			"73" : {"page" : "448", "juz" : "23"},
			"74" : {"page" : "448", "juz" : "23"},
			"75" : {"page" : "448", "juz" : "23"},
			"76" : {"page" : "448", "juz" : "23"},
			"77" : {"page" : "449", "juz" : "23"},
			"78" : {"page" : "449", "juz" : "23"},
			"79" : {"page" : "449", "juz" : "23"},
			"80" : {"page" : "449", "juz" : "23"},
			"81" : {"page" : "449", "juz" : "23"},
			"82" : {"page" : "449", "juz" : "23"},
			"83" : {"page" : "449", "juz" : "23"},
			"84" : {"page" : "449", "juz" : "23"},
			"85" : {"page" : "449", "juz" : "23"},
			"86" : {"page" : "449", "juz" : "23"},
			"87" : {"page" : "449", "juz" : "23"},
			"88" : {"page" : "449", "juz" : "23"},
			"89" : {"page" : "449", "juz" : "23"},
			"90" : {"page" : "449", "juz" : "23"},
			"91" : {"page" : "449", "juz" : "23"},
			"92" : {"page" : "449", "juz" : "23"},
			"93" : {"page" : "449", "juz" : "23"},
			"94" : {"page" : "449", "juz" : "23"},
			"95" : {"page" : "449", "juz" : "23"},
			"96" : {"page" : "449", "juz" : "23"},
			"97" : {"page" : "449", "juz" : "23"},
			"98" : {"page" : "449", "juz" : "23"},
			"99" : {"page" : "449", "juz" : "23"},
			"100" : {"page" : "449", "juz" : "23"},
			"101" : {"page" : "449", "juz" : "23"},
			"102" : {"page" : "449", "juz" : "23"},
			"103" : {"page" : "450", "juz" : "23"},
			"104" : {"page" : "450", "juz" : "23"},
			"105" : {"page" : "450", "juz" : "23"},
			"106" : {"page" : "450", "juz" : "23"},
			"107" : {"page" : "450", "juz" : "23"},
			"108" : {"page" : "450", "juz" : "23"},
			"109" : {"page" : "450", "juz" : "23"},
			"110" : {"page" : "450", "juz" : "23"},
			"111" : {"page" : "450", "juz" : "23"},
			"112" : {"page" : "450", "juz" : "23"},
			"113" : {"page" : "450", "juz" : "23"},
			"114" : {"page" : "450", "juz" : "23"},
			"115" : {"page" : "450", "juz" : "23"},
			"116" : {"page" : "450", "juz" : "23"},
			"117" : {"page" : "450", "juz" : "23"},
			"118" : {"page" : "450", "juz" : "23"},
			"119" : {"page" : "450", "juz" : "23"},
			"120" : {"page" : "450", "juz" : "23"},
			"121" : {"page" : "450", "juz" : "23"},
			"122" : {"page" : "450", "juz" : "23"},
			"123" : {"page" : "450", "juz" : "23"},
			"124" : {"page" : "450", "juz" : "23"},
			"125" : {"page" : "450", "juz" : "23"},
			"126" : {"page" : "450", "juz" : "23"},
			"127" : {"page" : "451", "juz" : "23"},
			"128" : {"page" : "451", "juz" : "23"},
			"129" : {"page" : "451", "juz" : "23"},
			"130" : {"page" : "451", "juz" : "23"},
			"131" : {"page" : "451", "juz" : "23"},
			"132" : {"page" : "451", "juz" : "23"},
			"133" : {"page" : "451", "juz" : "23"},
			"134" : {"page" : "451", "juz" : "23"},
			"135" : {"page" : "451", "juz" : "23"},
			"136" : {"page" : "451", "juz" : "23"},
			"137" : {"page" : "451", "juz" : "23"},
			"138" : {"page" : "451", "juz" : "23"},
			"139" : {"page" : "451", "juz" : "23"},
			"140" : {"page" : "451", "juz" : "23"},
			"141" : {"page" : "451", "juz" : "23"},
			"142" : {"page" : "451", "juz" : "23"},
			"143" : {"page" : "451", "juz" : "23"},
			"144" : {"page" : "451", "juz" : "23"},
			"145" : {"page" : "451", "juz" : "23"},
			"146" : {"page" : "451", "juz" : "23"},
			"147" : {"page" : "451", "juz" : "23"},
			"148" : {"page" : "451", "juz" : "23"},
			"149" : {"page" : "451", "juz" : "23"},
			"150" : {"page" : "451", "juz" : "23"},
			"151" : {"page" : "451", "juz" : "23"},
			"152" : {"page" : "451", "juz" : "23"},
			"153" : {"page" : "451", "juz" : "23"},
			"154" : {"page" : "452", "juz" : "23"},
			"155" : {"page" : "452", "juz" : "23"},
			"156" : {"page" : "452", "juz" : "23"},
			"157" : {"page" : "452", "juz" : "23"},
			"158" : {"page" : "452", "juz" : "23"},
			"159" : {"page" : "452", "juz" : "23"},
			"160" : {"page" : "452", "juz" : "23"},
			"161" : {"page" : "452", "juz" : "23"},
			"162" : {"page" : "452", "juz" : "23"},
			"163" : {"page" : "452", "juz" : "23"},
			"164" : {"page" : "452", "juz" : "23"},
			"165" : {"page" : "452", "juz" : "23"},
			"166" : {"page" : "452", "juz" : "23"},
			"167" : {"page" : "452", "juz" : "23"},
			"168" : {"page" : "452", "juz" : "23"},
			"169" : {"page" : "452", "juz" : "23"},
			"170" : {"page" : "452", "juz" : "23"},
			"171" : {"page" : "452", "juz" : "23"},
			"172" : {"page" : "452", "juz" : "23"},
			"173" : {"page" : "452", "juz" : "23"},
			"174" : {"page" : "452", "juz" : "23"},
			"175" : {"page" : "452", "juz" : "23"},
			"176" : {"page" : "452", "juz" : "23"},
			"177" : {"page" : "452", "juz" : "23"},
			"178" : {"page" : "452", "juz" : "23"},
			"179" : {"page" : "452", "juz" : "23"},
			"180" : {"page" : "452", "juz" : "23"},
			"181" : {"page" : "452", "juz" : "23"},
			"182" : {"page" : "452", "juz" : "23"}
		}
	}
}